LICENSE
MANIFEST.in
README
setup.py
django_dynamicpages.egg-info/PKG-INFO
django_dynamicpages.egg-info/SOURCES.txt
django_dynamicpages.egg-info/dependency_links.txt
django_dynamicpages.egg-info/not-zip-safe
django_dynamicpages.egg-info/top_level.txt
dynamic_pages/__init__.py
dynamic_pages/admin.py
dynamic_pages/models.py
dynamic_pages/settings.py
dynamic_pages/tests.py
dynamic_pages/urls.py
dynamic_pages/views.py
dynamic_pages/context_processors/__init__.py
dynamic_pages/dynamic/__init__.py
dynamic_pages/dynamic/dynamic_urls.py
dynamic_pages/dynamic/utils.py
dynamic_pages/form/__init__.py
dynamic_pages/form/page.py
dynamic_pages/locale/cs/LC_MESSAGES/django.po
dynamic_pages/middleware/__init__.py
dynamic_pages/static/dynamic_pages/js/jquery-1.6.4.min.js
dynamic_pages/static/dynamic_pages/js/pages.js
dynamic_pages/templates/admin_tp/404.html
dynamic_pages/templates/admin_tp/500.html
dynamic_pages/templates/admin_tp/actions.html
dynamic_pages/templates/admin_tp/app_index.html
dynamic_pages/templates/admin_tp/base.html
dynamic_pages/templates/admin_tp/base_site.html
dynamic_pages/templates/admin_tp/change_form.html
dynamic_pages/templates/admin_tp/change_list.html
dynamic_pages/templates/admin_tp/change_list_results.html
dynamic_pages/templates/admin_tp/date_hierarchy.html
dynamic_pages/templates/admin_tp/delete_confirmation.html
dynamic_pages/templates/admin_tp/delete_selected_confirmation.html
dynamic_pages/templates/admin_tp/filter.html
dynamic_pages/templates/admin_tp/index.html
dynamic_pages/templates/admin_tp/invalid_setup.html
dynamic_pages/templates/admin_tp/login.html
dynamic_pages/templates/admin_tp/object_history.html
dynamic_pages/templates/admin_tp/pagination.html
dynamic_pages/templates/admin_tp/prepopulated_fields_js.html
dynamic_pages/templates/admin_tp/search_form.html
dynamic_pages/templates/admin_tp/submit_line.html
dynamic_pages/templates/admin_tp/auth/user/add_form.html
dynamic_pages/templates/admin_tp/auth/user/change_password.html
dynamic_pages/templates/admin_tp/edit_inline/stacked.html
dynamic_pages/templates/admin_tp/edit_inline/tabular.html
dynamic_pages/templates/admin_tp/includes/fieldset.html
dynamic_pages/templatetags/__init__.py
